seagulls/seagulls_cli/__init__.py
seagulls/seagulls_cli/_application.py
seagulls/seagulls_cli/_container_repository.py
seagulls/seagulls_cli/_di_container.py
seagulls/seagulls_cli/_entry_point.py
seagulls/seagulls_cli/_logging_client.py
seagulls/seagulls_cli/py.typed
seagulls_cli-0.1.0rc1.dist-info/entry_points.txt
seagulls_cli-0.1.0rc1.dist-info/WHEEL
seagulls_cli-0.1.0rc1.dist-info/METADATA
seagulls_cli-0.1.0rc1.dist-info/RECORD
